leagueregistrar/__init__.py
leagueregistrar/dbutils.py
leagueregistrar/models.py
leagueregistrar/registrar.py
leagueregistrar/types.py
league_registrar-0.0.1.dist-info/LICENSE
league_registrar-0.0.1.dist-info/METADATA
league_registrar-0.0.1.dist-info/WHEEL
league_registrar-0.0.1.dist-info/top_level.txt
league_registrar-0.0.1.dist-info/RECORD
