Metadata-Version: 2.1
Name: league-registrar
Version: 0.0.1
Summary: A system for programatically keeping track of league data
Author-email: "Tanner B. Corcoran" <tannerbcorcoran@gmail.com>
Project-URL: Homepage, https://github.com/tanrbobanr/league-registrar
Classifier: Programming Language :: Python :: 3
Classifier: License :: OSI Approved :: MIT License
Classifier: Operating System :: OS Independent
Requires-Python: >=3.11
License-File: LICENSE
Requires-Dist: prepr (>=0.0.6)
